mineCube/__init__.py
mineCube/core/__init__.py
mineCube/core/config.py
mineCube/core/helpers/__init__.py
mineCube/core/helpers/cell.py
mineCube/core/helpers/colaborative_dependency_graph.py
mineCube/core/helpers/date.py
mineCube/core/helpers/dependency_graph.py
mineCube/core/helpers/follow_counter.py
mineCube/core/helpers/load_cube.py
mineCube/core/helpers/merge_lists.py
mineCube/core/helpers/mixed_cube.py
mineCube/core/helpers/save_cube.py
mineCube/core/helpers/sum_nested_list.py
mineCube/core/helpers/algo/HM.py
mineCube/core/helpers/algo/__init__.py
mineCube/core/helpers/algo/modified_HM.py
mineCube/core/offline/__init__.py
mineCube/core/offline/process_cube.py
mineCube/core/streaming/__init__.py
mineCube/core/streaming/loader.py
mineCube/core/streaming/mini_cube.py
mineCube/core/streaming/stream_bucket.py
mineCube/core/streaming/stream_manager.py
mineCube/core/streaming/stream_processor.py
mineCube/web_ui/__init__.py
mineCube/web_ui/app.py
mineCube-0.1.4.dist-info/METADATA
mineCube-0.1.4.dist-info/WHEEL
mineCube-0.1.4.dist-info/top_level.txt
mineCube-0.1.4.dist-info/RECORD
