Metadata-Version: 2.1
Name: mineCube
Version: 0.1.4
Summary: MineCube a lib for creating process cubes in offline, streaming or even mixed modes.
Author: Abdellatif Ahammad
Requires-Dist: pandas
Requires-Dist: Flask
Requires-Dist: Flask-Cors
